[
  {
    "date": "20240301",
    "title": "Annual Shareholder Letter Published",
    "type": "press_release",
    "url": "https://www.berkshirehathaway.com/letters/2023ltr.pdf",
    "source": "https://web.archive.org/web/20240301120000/https://www.berkshirehathaway.com/letters/2023ltr.pdf"
  },
  {
    "date": "20240214",
    "title": "Form 13F-HR Filed",
    "type": "13F",
    "url": "https://www.sec.gov/Archives/edgar/data/1067983/000095012324001234/xslForm13F_X01/primary_doc.xml",
    "source": "https://www.sec.gov/Archives/edgar/data/1067983/000095012324001234/xslForm13F_X01/primary_doc.xml"
  }
]